bibtex_dblp/__init__.py
bibtex_dblp/database.py
bibtex_dblp/dblp_api.py
bibtex_dblp/dblp_data.py
bibtex_dblp/io.py
bibtex_dblp/search.py
bin/convert_dblp.py
bin/import_dblp.py
bin/modify_bibtex.py
bin/update_from_dblp.py
bibtex_dblp-1.0.1.dist-info/METADATA
bibtex_dblp-1.0.1.dist-info/WHEEL
bibtex_dblp-1.0.1.dist-info/entry_points.txt
bibtex_dblp-1.0.1.dist-info/licenses/LICENSE
bibtex_dblp-1.0.1.dist-info/RECORD
