Metadata-Version: 2.4
Name: bibtex-dblp
Version: 1.0.1
Summary: Create and revise bibtex entries from DBLP.
Project-URL: Homepage, https://github.com/volkm/bibtex-dblp
Project-URL: Bug Tracker, https://github.com/volkm/bibtex-dblp/issues
Author-email: "M. Volk" <m.volk@tue.nl>
License-Expression: GPL-3.0-or-later
License-File: LICENSE
Requires-Python: >=3.10
Requires-Dist: pybtex
Requires-Dist: pyperclip
Requires-Dist: requests
Requires-Dist: requests-ratelimiter
Provides-Extra: dev
Requires-Dist: black; extra == 'dev'
Provides-Extra: test
Requires-Dist: pytest; extra == 'test'
